SyncData-0.1.16.dist-info/DESCRIPTION.rst
SyncData-0.1.16.dist-info/METADATA
SyncData-0.1.16.dist-info/RECORD
SyncData-0.1.16.dist-info/WHEEL
SyncData-0.1.16.dist-info/metadata.json
SyncData-0.1.16.dist-info/top_level.txt
syncdata/__init__.py
syncdata/models.py
syncdata/syncdata.py
syncdata/services/__init__.py
syncdata/services/execute_log.py
syncdata/services/sync_data.py
