Metadata-Version: 2.0
Name: SyncData
Version: 0.1.16
Summary: Sync client and server data
Home-page: https://github.com/kuanger/SyncData
Author: hausir
Author-email: hausir@icloud.com
License: MIT
Platform: a
Platform: n
Platform: y
Requires-Dist: SQLAlchemy (>=1.1.4)
Requires-Dist: redis (>=2.10.5)
